quakefeeds-0.2.dist-info/WHEEL
quakefeeds-0.2.dist-info/DESCRIPTION.rst
quakefeeds-0.2.dist-info/metadata.json
quakefeeds-0.2.dist-info/top_level.txt
quakefeeds-0.2.dist-info/RECORD
quakefeeds-0.2.dist-info/entry_points.txt
quakefeeds-0.2.dist-info/METADATA
quakefeeds/__init__.py
quakefeeds/scripts/quakestats.py
quakefeeds/scripts/__init__.py
quakefeeds/scripts/quakemap.py
quakefeeds/templates/plain.html
quakefeeds/templates/titled.html
