Metadata-Version: 2.0
Name: quakefeeds
Version: 0.2
Summary: Python 3 tools for handling USGS earthquake data feeds
Home-page: https://github.com/python33r/quakefeeds
Author: Nick Efford
Author-email: nick.efford@gmail.com
License: MIT
Keywords: data json science seismology usgs
Platform: any
Classifier: Programming Language :: Python
Classifier: Programming Language :: Python :: 3.4
Classifier: Development Status :: 4 - Beta
Classifier: License :: OSI Approved :: MIT License
Classifier: Operating System :: OS Independent
Classifier: Intended Audience :: Developers
Classifier: Intended Audience :: Science/Research
Classifier: Topic :: Software Development :: Libraries :: Python Modules
Classifier: Topic :: Scientific/Engineering
Requires-Dist: Requests
Requires-Dist: Jinja2
Requires-Dist: docopt
